version_test/__init__.py
version_test-0.1.35.dist-info/METADATA
version_test-0.1.35.dist-info/WHEEL
version_test-0.1.35.dist-info/RECORD
